imagecaptioner/__init__.py
imagecaptioner/captioner.py
imagecaptioner/cli.py
imagecaptioner/metatags.py
imagecaptioner/utils.py
imagecaptioner/fonts/Lato-Regular.ttf
imagecaptioner-0.4.dist-info/METADATA
imagecaptioner-0.4.dist-info/WHEEL
imagecaptioner-0.4.dist-info/entry_points.txt
imagecaptioner-0.4.dist-info/top_level.txt
imagecaptioner-0.4.dist-info/RECORD
