Metadata-Version: 2.1
Name: imagecaptioner
Version: 0.4
Summary: Command line python script for adding captions to the images based on the metadata, filename or user input
Home-page: https://github.com/greencashew/image-captioner
Author: Jan Górkiewicz (https://greencashew.dev/)
License: MIT
Platform: UNKNOWN
Requires-Dist: Pillow
Requires-Dist: datefinder
